setup.py
django_rest_apikey/__init__.py
django_rest_apikey/admin.py
django_rest_apikey/authentication.py
django_rest_apikey/models.py
django_rest_apikey/serializers.py
django_rest_apikey/validators.py
django_rest_apikey/views.py
django_rest_apikey.egg-info/PKG-INFO
django_rest_apikey.egg-info/SOURCES.txt
django_rest_apikey.egg-info/dependency_links.txt
django_rest_apikey.egg-info/requires.txt
django_rest_apikey.egg-info/top_level.txt
django_rest_apikey/migrations/0001_initial.py
django_rest_apikey/migrations/__init__.py