Metadata-Version: 1.1
Name: django-rest-apikey
Version: 0.1.0
Summary: Per-user API key to authenticate in Django REST Framework
Home-page: https://github.com/ybulach/django-rest-apikey
Author: Yamine BULACH
Author-email: contact@yamine-bulach.eu
License: LGPL
Platform: UNKNOWN
Classifier: Development Status :: 4 - Beta
Classifier: Environment :: Web Environment
Classifier: Framework :: Django
Classifier: License :: OSI Approved :: GNU Library or Lesser General Public License (LGPL)
Classifier: Operating System :: OS Independent
Classifier: Programming Language :: Python :: 2.7
Classifier: Topic :: Software Development :: Libraries :: Python Modules
Classifier: Framework :: Django
